mkenv.py
pyenv_mkenv-1.0.0.dist-info/LICENSE
pyenv_mkenv-1.0.0.dist-info/METADATA
pyenv_mkenv-1.0.0.dist-info/WHEEL
pyenv_mkenv-1.0.0.dist-info/entry_points.txt
pyenv_mkenv-1.0.0.dist-info/top_level.txt
pyenv_mkenv-1.0.0.dist-info/RECORD
