Metadata-Version: 2.1
Name: pyenv-mkenv
Version: 1.0.0
Summary: Simple script to help create and use pyenv virtualenvs
Home-page: https://github.com/clbarnes/pyenv-mkenv
Author: Chris L. Barnes
Author-email: chrislloydbarnes@gmail.com
License: UNKNOWN
Keywords: pyenv virtualenv venv requirements
Platform: UNKNOWN
Classifier: Development Status :: 4 - Beta
Classifier: Intended Audience :: Developers
Classifier: Topic :: Software Development :: Build Tools
Classifier: License :: OSI Approved :: MIT License
Classifier: Programming Language :: Python :: 3
Classifier: Programming Language :: Python :: 3.6
Classifier: Programming Language :: Python :: 3.7
Classifier: Programming Language :: Python :: 3.8
Requires-Python: >=3.6
